{"AccurateCountDown": 51, "AetherSense": 71, "ChatBubbles": 98, "OopsAllLalafells": 55, "QoLBar": 38, "Tourist": 41, "PeepingTom": 64, "SoundSetter": 12, "StarlightBreaker": 96, "MacroRecursion": 49, "Dalamud.LoadingImage": 76, "PlayerTrack": 42, "PriceCheck": 70, "Globetrotter": 78, "MOAction": 39, "FPSPlugin": 68, "VFXEditor": 20, "SimpleTweaksPlugin": 91, "EasyEyes": 64, "Dalamud.RichPresence": 9, "RemindMe": 78, "TitleEdit": 12, "Visibility": 50, "ItemSearchPlugin": 48, "IMEPlugin": 47, "PennyPincher": 41, "MarketBoardPlugin": 73, "GoodMemory": 90, "WaymarkPresetPlugin": 30, "TeleporterPlugin": 27, "GatherBuddy": 46, "Kapture": 19, "PingPlugin": 39, "PixelPerfect": 32, "JobIcons": 50, "BetterPartyFinder": 36, "SlideCast": 91, "RezPls": 58, "DamageInfoPlugin": 66, "MPTimer": 36, "XIVCombo": 71, "Housemate": 49, "orchestrion": 24, "ChatCoordinates": 21, "WinTitle": 20, "MapLinker": 14}