{"AccurateCountDown": 274, "AetherSense": 384, "ChatBubbles": 691, "OopsAllLalafells": 278, "QoLBar": 242, "Tourist": 234, "PeepingTom": 285, "SoundSetter": 69, "StarlightBreaker": 526, "MacroRecursion": 204, "Dalamud.LoadingImage": 345, "PlayerTrack": 199, "PriceCheck": 358, "Globetrotter": 465, "MOAction": 185, "FPSPlugin": 358, "VFXEditor": 140, "SimpleTweaksPlugin": 509, "EasyEyes": 252, "Dalamud.RichPresence": 56, "RemindMe": 366, "TitleEdit": 68, "Visibility": 194, "ItemSearchPlugin": 236, "IMEPlugin": 231, "PennyPincher": 197, "MarketBoardPlugin": 421, "GoodMemory": 425, "WaymarkPresetPlugin": 133, "TeleporterPlugin": 157, "GatherBuddy": 189, "Kapture": 103, "PingPlugin": 199, "PixelPerfect": 190, "JobIcons": 411, "BetterPartyFinder": 193, "SlideCast": 468, "RezPls": 286, "DamageInfoPlugin": 316, "MPTimer": 155, "XIVCombo": 378, "Housemate": 251, "orchestrion": 107, "ChatCoordinates": 134, "WinTitle": 88, "MapLinker": 70, "SkillSwap": 143, "SoundFilter": 38, "BrowserHost.Plugin": 1, "DeepDungeonDex": 172}